djangorestframework_jsonp-1.0.2.dist-info/DESCRIPTION.rst
djangorestframework_jsonp-1.0.2.dist-info/METADATA
djangorestframework_jsonp-1.0.2.dist-info/metadata.json
djangorestframework_jsonp-1.0.2.dist-info/RECORD
djangorestframework_jsonp-1.0.2.dist-info/top_level.txt
djangorestframework_jsonp-1.0.2.dist-info/WHEEL
rest_framework_jsonp/__init__.py
rest_framework_jsonp/compat.py
rest_framework_jsonp/renderers.py
